SKILL_TEST_GAME/skill_test_game.py
SKILL_TEST_GAME-1.dist-info/LICENSE
SKILL_TEST_GAME-1.dist-info/METADATA
SKILL_TEST_GAME-1.dist-info/WHEEL
SKILL_TEST_GAME-1.dist-info/entry_points.txt
SKILL_TEST_GAME-1.dist-info/top_level.txt
SKILL_TEST_GAME-1.dist-info/RECORD
