Metadata-Version: 2.1
Name: SKILL-TEST-GAME
Version: 1
Summary: This package contains implementation of the game "Skill Test Game". This game is about taking skill tests and earning skill badges.
Home-page: https://github.com/DigitalCreativeApkDev/SKILL_TEST_GAME
Author: DigitalCreativeApkDev
Author-email: digitalcreativeapkdev2022@gmail.com
License: MIT
Platform: UNKNOWN
Classifier: Programming Language :: Python :: 3
Classifier: Programming Language :: Python :: 3.7
